addition_numpy_pytorch_package/__init__.py
addition_numpy_pytorch_package/addition.py
addition_numpy_pytorch_package/multiplication.py
addition_numpy_pytorch_package-0.1.3.dist-info/METADATA
addition_numpy_pytorch_package-0.1.3.dist-info/WHEEL
addition_numpy_pytorch_package-0.1.3.dist-info/top_level.txt
addition_numpy_pytorch_package-0.1.3.dist-info/RECORD
