Metadata-Version: 2.4
Name: addition-numpy-pytorch-package
Version: 0.1.3
Summary: Add your description here
Author-email: Yerly Sevan <sevan.yerly@he-arc.ch>
Requires-Python: >=3.12
Requires-Dist: numpy>=2.2.6
